[
  {
    "id": 1,
    "image": "./images/arctic-fox.png",
    "alt": "antelope"
  },
  {
    "id": 2,
    "image": "./images/snake.png",
    "alt": "snake"
  },
  {
    "id": 3,
    "image": "./images/fox.png",
    "alt": "fox"
  },
  {
    "id": 4,
    "image": "./images/hummingbird.png",
    "alt": "hummingbird"
  },
  {
    "id": 5,
    "image": "./images/polar-bear.png",
    "alt": "polar bear"
  },
  {
    "id": 6,
    "image": "./images/seaturtle.png",
    "alt": "sea turtle"
  },
  {
    "id": 7,
    "image": "./images/gorilla.png",
    "alt": "gorilla"
  },
  {
    "id": 8,
    "image": "./images/penguins.png",
    "alt": "penguins"
  },
  {
    "id": 9,
    "image": "./images/giraffes.png",
    "alt": "giraffes"
  },
  {
    "id": 10,
    "image": "./images/elephants.png",
    "alt": "elephants"
  },
  {
    "id": 11,
    "image": "./images/bear.png",
    "alt": "bears"
  },
  {
    "id": 12,
    "image": "./images/rhino.png",
    "alt": "rhino"
  }
]